huaweicloudsdkcbs/__init__.py
huaweicloudsdkcbs/v1/__init__.py
huaweicloudsdkcbs/v1/cbs_async_client.py
huaweicloudsdkcbs/v1/cbs_client.py
huaweicloudsdkcbs/v1/model/__init__.py
huaweicloudsdkcbs/v1/model/answers.py
huaweicloudsdkcbs/v1/model/basic_list_resp.py
huaweicloudsdkcbs/v1/model/candidate_intention.py
huaweicloudsdkcbs/v1/model/character.py
huaweicloudsdkcbs/v1/model/character_config.py
huaweicloudsdkcbs/v1/model/character_dimension.py
huaweicloudsdkcbs/v1/model/character_position.py
huaweicloudsdkcbs/v1/model/chat_answers.py
huaweicloudsdkcbs/v1/model/collect_hot_questions_request.py
huaweicloudsdkcbs/v1/model/collect_hot_questions_response.py
huaweicloudsdkcbs/v1/model/collect_key_words_request.py
huaweicloudsdkcbs/v1/model/collect_key_words_response.py
huaweicloudsdkcbs/v1/model/collect_reply_rates_request.py
huaweicloudsdkcbs/v1/model/collect_reply_rates_response.py
huaweicloudsdkcbs/v1/model/collect_session_stats_request.py
huaweicloudsdkcbs/v1/model/collect_session_stats_response.py
huaweicloudsdkcbs/v1/model/create_res.py
huaweicloudsdkcbs/v1/model/create_session_request.py
huaweicloudsdkcbs/v1/model/create_session_response.py
huaweicloudsdkcbs/v1/model/create_video_req.py
huaweicloudsdkcbs/v1/model/current_slot.py
huaweicloudsdkcbs/v1/model/delete_session_request.py
huaweicloudsdkcbs/v1/model/delete_session_response.py
huaweicloudsdkcbs/v1/model/doc_bot_answers.py
huaweicloudsdkcbs/v1/model/doc_query_answer_detail.py
huaweicloudsdkcbs/v1/model/ex_questions.py
huaweicloudsdkcbs/v1/model/execute_compose_video_ondemand_request.py
huaweicloudsdkcbs/v1/model/execute_compose_video_ondemand_response.py
huaweicloudsdkcbs/v1/model/execute_compose_video_request.py
huaweicloudsdkcbs/v1/model/execute_compose_video_response.py
huaweicloudsdkcbs/v1/model/execute_create_video_request.py
huaweicloudsdkcbs/v1/model/execute_create_video_response.py
huaweicloudsdkcbs/v1/model/execute_delete_video_by_id_request.py
huaweicloudsdkcbs-3.1.184.dist-info/METADATA
huaweicloudsdkcbs-3.1.184.dist-info/WHEEL
huaweicloudsdkcbs-3.1.184.dist-info/licenses/LICENSE
huaweicloudsdkcbs-3.1.184.dist-info/RECORD
